Metadata-Version: 1.0
Name: distributions-nk
Version: 0.1
Summary: Gaussian,Binomial distributions
Home-page: UNKNOWN
Author: UNKNOWN
Author-email: UNKNOWN
License: UNKNOWN
Platform: UNKNOWN
